.coveragerc
.gitignore
.nojekyll
.releaserc.json
AUTHORS.md
CONTRIBUTING.md
HISTORY.md
HISTORY.old.md
LICENSE
README.md
index.html
package-lock.json
package.json
pyproject.toml
.devcontainer/Dockerfile
.devcontainer/devcontainer.json
.devcontainer/docker-compose.yml
.devcontainer/supporting_files/configuration/.czrc
.devcontainer/supporting_files/configuration/.p10k.zsh
.devcontainer/supporting_files/configuration/.zshrc
.devcontainer/supporting_files/configuration/p10k-instant-prompt-vscode.zsh
.devcontainer/supporting_files/scripts/post-create.sh
.github/dependabot.yml
.github/workflows/release.yml
.github/workflows/test.yml
centralnicreseller/__init__.py
centralnicreseller.apiconnector.egg-info/PKG-INFO
centralnicreseller.apiconnector.egg-info/SOURCES.txt
centralnicreseller.apiconnector.egg-info/dependency_links.txt
centralnicreseller.apiconnector.egg-info/requires.txt
centralnicreseller.apiconnector.egg-info/top_level.txt
centralnicreseller/apiconnector/__init__.py
centralnicreseller/apiconnector/apiclient.py
centralnicreseller/apiconnector/column.py
centralnicreseller/apiconnector/customlogger.py
centralnicreseller/apiconnector/idnaconverter.py
centralnicreseller/apiconnector/idnaprocessor.py
centralnicreseller/apiconnector/logger.py
centralnicreseller/apiconnector/record.py
centralnicreseller/apiconnector/response.py
centralnicreseller/apiconnector/responseparser.py
centralnicreseller/apiconnector/responsetemplate.py
centralnicreseller/apiconnector/responsetemplatemanager.py
centralnicreseller/apiconnector/socketconfig.py
htmlcov/.gitignore
htmlcov/class_index.html
htmlcov/coverage_html_cb_6fb7b396.js
htmlcov/favicon_32_cb_58284776.png
htmlcov/function_index.html
htmlcov/index.html
htmlcov/keybd_closed_cb_ce680311.png
htmlcov/status.json
htmlcov/style_cb_8e611ae1.css
scripts/coverage.sh
scripts/createdistribution.sh
scripts/uploaddistribution_live.sh
scripts/uploaddistribution_test.sh
tests/app.py
tests/test_apiclient.py
tests/test_column.py
tests/test_idnaconverter.py
tests/test_record.py
tests/test_response.py
tests/test_responsetemplate.py
tests/test_responsetemplatemanager.py
tests/test_socketconfig.py