Metadata-Version: 2.1
Name: centralnicreseller.apiconnector
Version: 5.0.0
Summary: centralnicreseller.apiconnector is an API connector library for the insanely fast CentralNic Reseller (fka. RRPProxy) Backend API.
Author-email: Kai Schwarz <kai.schwarz@centralnic.com>, Asif Nawaz <asif.nawaz@centralnic.com>
Maintainer-email: Kai Schwarz <kai.schwarz@centralnic.com>, Asif Nawaz <asif.nawaz@centralnic.com>
License: MIT License
Project-URL: homepage, https://github.com/centralnicgroup-opensource/rtldev-middleware-python-sdk/
Classifier: Programming Language :: Python :: 3
Classifier: License :: OSI Approved :: MIT License
Classifier: Operating System :: OS Independent
License-File: LICENSE
License-File: AUTHORS.md
Requires-Dist: docutils<1,>=0
Requires-Dist: sphinx-rtd-theme<4,>=1
Requires-Dist: m2r2<1,>=0
Requires-Dist: pytest-cov<6,>=2
Requires-Dist: sphinx<9,>=3
Requires-Dist: sphinxcontrib-log-cabinet<2,>=1
Requires-Dist: sphinxcontrib-websupport<3,>=1
Requires-Dist: twine<6,>=4
Requires-Dist: black<25,>=23
Requires-Dist: idna>=3
